frequenz/reporting/__init__.py
frequenz/reporting/_reporting.py
frequenz/reporting/conftest.py
frequenz/reporting/py.typed
frequenz_reporting_python-0.5.0.dist-info/licenses/LICENSE
frequenz_reporting_python-0.5.0.dist-info/METADATA
frequenz_reporting_python-0.5.0.dist-info/WHEEL
frequenz_reporting_python-0.5.0.dist-info/top_level.txt
frequenz_reporting_python-0.5.0.dist-info/RECORD
